xk_utils/__init__.py
xk_utils/logger/__init__.py
xk_utils/logger/handler.py
xk_utils/mail/__init__.py
xk_utils/mail/config.py
xk_utils/mail/mail_consumer.py
xk_utils/mail/mail_producer.py
xk_utils/mail/send.py
xk_utils-0.0.7.dist-info/METADATA
xk_utils-0.0.7.dist-info/WHEEL
xk_utils-0.0.7.dist-info/top_level.txt
xk_utils-0.0.7.dist-info/RECORD
