Metadata-Version: 2.1
Name: xk-utils
Version: 0.0.7
Summary: xing kuang utils
Home-page: https://hd.devcloud.huaweicloud.com/codehub/project/06cd251a973b4830bc9f5d31d2cc03e5/codehub/140018268/home
Author: zhanglei
Author-email: zhanglei1@cls.cn
License: MIT Licence
Project-URL: Bug Tracker, https://github.com/pypa/sampleproject/issues
Platform: UNKNOWN
Classifier: Programming Language :: Python :: 3
Classifier: License :: OSI Approved :: MIT License
Classifier: Operating System :: OS Independent
Requires-Python: >=3.7
Requires-Dist: redis (>=3.5.3)
